bigdata_client/__init__.py
bigdata_client/advanced_search_query.py
bigdata_client/api/__init__.py
bigdata_client/api/chat.py
bigdata_client/api/knowledge_graph.py
bigdata_client/api/search.py
bigdata_client/api/subscription.py
bigdata_client/api/uploads.py
bigdata_client/api/watchlist.py
bigdata_client/auth.py
bigdata_client/bigdata.py
bigdata_client/clerk/__init__.py
bigdata_client/clerk/authenticators/__init__.py
bigdata_client/clerk/authenticators/base_instance.py
bigdata_client/clerk/authenticators/dev_instance.py
bigdata_client/clerk/authenticators/production_instance.py
bigdata_client/clerk/constants.py
bigdata_client/clerk/exceptions.py
bigdata_client/clerk/models.py
bigdata_client/clerk/sign_in_strategies/__init__.py
bigdata_client/clerk/sign_in_strategies/base.py
bigdata_client/clerk/sign_in_strategies/password.py
bigdata_client/clerk/token_manager.py
bigdata_client/clerk/token_manager_factory.py
bigdata_client/connection.py
bigdata_client/connection_management.py
bigdata_client/connection_protocol.py
bigdata_client/constants.py
bigdata_client/daterange.py
bigdata_client/document.py
bigdata_client/enum_utils.py
bigdata_client/environments/default
bigdata_client/exceptions.py
bigdata_client/jwt_utils.py
bigdata_client/models/__init__.py
bigdata_client/models/advanced_search_query.py
bigdata_client/models/chat.py
bigdata_client/models/comentions.py
bigdata_client/models/document.py
bigdata_client/models/entities.py
bigdata_client/models/languages.py
bigdata_client/models/search.py
bigdata_client/models/sharing.py
bigdata_client/models/sources.py
bigdata_client/models/subscription.py
bigdata_client/models/topics.py
bigdata_client/models/uploads.py
bigdata_client/models/watchlists.py
bigdata_client/pdf_utils.py
bigdata_client/query.py
bigdata_client/query_type.py
bigdata_client/search.py
bigdata_client/services/__init__.py
bigdata_client/services/chat_service.py
bigdata_client/services/content_search.py
bigdata_client/services/knowledge_graph.py
bigdata_client-2.19.1.dist-info/LICENSE
bigdata_client-2.19.1.dist-info/METADATA
bigdata_client-2.19.1.dist-info/WHEEL
bigdata_client-2.19.1.dist-info/RECORD
